{"_id":"a3b46210-1991-4eaf-a93c-e9040574f7df","name":"321","price":321,"launchDate":"2025-11-18T23:13:00","isCracked":false,"version":18,"userId":"1","photo":"http://localhost:8100/api/games/a3b46210-1991-4eaf-a93c-e9040574f7df/photo","lat":36.38882701339206,"lng":101.42584331285386}
{"_id":"f0f80364-2d8e-4bd3-9abe-2a18a91a2446","name":"dadas","price":32131,"launchDate":"2025-11-27T23:13:00","isCracked":false,"version":6,"userId":"1","photo":"http://localhost:8100/api/games/f0f80364-2d8e-4bd3-9abe-2a18a91a2446/photo","lat":46.25601249732375,"lng":23.17307748998592}
{"_id":"fe6e0c7b-20d2-4056-a2e1-57af0ce6faab","name":"dasdasdsad","price":312233,"launchDate":"2025-11-11T23:18:00","isCracked":false,"version":8,"userId":"1","photo":"http://localhost:8100/api/games/fe6e0c7b-20d2-4056-a2e1-57af0ce6faab/photo","lat":46.7712,"lng":23.6236}
{"_id":"3432b941-ddf3-406d-a9a4-91a4b25011db","name":"dasas","price":321,"launchDate":"2025-11-04T00:00:00.000Z","isCracked":true,"version":1,"userId":"2"}
{"_id":"b243dd6c-397b-44e1-90fd-07c29fe6142e","name":"ws","price":321,"launchDate":"2025-11-26T00:00:00.000Z","isCracked":false,"version":1,"userId":"2"}
{"_id":"b243dd6c-397b-44e1-90fd-07c29fe6142e","name":"ws1","price":321,"launchDate":"2025-11-26T00:00:00.000Z","isCracked":false,"version":2,"userId":"2"}
{"_id":"b243dd6c-397b-44e1-90fd-07c29fe6142e","name":"ws1","price":321,"launchDate":"2025-11-26T00:00:00.000Z","isCracked":true,"version":3,"userId":"2"}
